[
  {
    "rank": 1,
    "solution": "Turn on incremental attribution",
    "what_it_solves": "Counts only conversions Meta drove. Cleaner ROAS reads.",
    "activate_it": [
      "Ads Manager → Account Settings → Attribution Setting → enable Incremental Attribution",
      "Confirm with analytics team to avoid double-counting in BI dashboards",
      "Add 'Incremental Conversions' column in reporting view",
      "Re-baseline ROAS reads after 14d to capture cleaner attribution"
    ],
    "priority": "Critical",
    "adoption_pct": 0,
    "stage": "Pitched",
    "expected_lift": "Understanding true incremental impact",
    "references": [
      "Meta Attribution Setting Guide 2025"
    ],
    "tags": "",
    "hidden_by_default": false
  },
  {
    "rank": 2,
    "solution": "Scale Partnership Ads",
    "what_it_solves": "Creator/UGC signal at scale. Brand amplification format.",
    "activate_it": [
      "Identify creator/UGC partners aligned with brand (use Brand Collabs Manager)",
      "Set up Partnership Ads in existing campaigns (Ads Manager → Ad level → Partnership Ad toggle)",
      "Test 3-5 creator concepts in same ad set as BAU creative",
      "Enable Dynamic Header Optimization for creative variation",
      "Compare CTR + CPA vs standard ads → scale winners 20%+"
    ],
    "priority": "Critical",
    "adoption_pct": 0,
    "stage": "Pitched",
    "expected_lift": "+25% CTR vs standard ads",
    "references": [
      "Meta Partnership Ads Benchmarks 2025",
      "Meta Creator Marketing Insights"
    ],
    "tags": "",
    "hidden_by_default": false
  },
  {
    "rank": 3,
    "solution": "Run single-cell Conversion Lift test",
    "what_it_solves": "Causal measurement, not correlation. Defends spend.",
    "activate_it": [
      "Open Ads Manager → Experiments → Conversion Lift",
      "Define one test cell on top-spending campaign (min. $10k spend, 7-day window)",
      "Configure conversion event + holdout group (Meta team can run setup for you)",
      "Review lift report at end of test → use to defend run-rate vs CFO"
    ],
    "priority": "Critical",
    "adoption_pct": 0,
    "stage": "Pitched",
    "expected_lift": "Quantified causal lift measurement",
    "references": [
      "Meta Conversion Lift Methodology 2025"
    ],
    "tags": "",
    "hidden_by_default": false
  },
  {
    "rank": 4,
    "solution": "Simplify or consolidate ad sets",
    "what_it_solves": "Faster learning phase. Less fragmentation = better delivery.",
    "activate_it": [
      "Simplify or consolidate ad sets"
    ],
    "priority": "Critical",
    "adoption_pct": 0,
    "stage": "Pitched",
    "expected_lift": "+5% lower CPA",
    "references": [],
    "tags": "",
    "hidden_by_default": false
  },
  {
    "rank": 5,
    "solution": "App value optimization (ROAS)",
    "what_it_solves": "Same logic, app surface. Top lever for app advertisers.",
    "activate_it": [
      "Audit Pixel/SDK value event coverage (Events Manager → Test Events)",
      "Confirm value parity vs MMP (AppsFlyer / Adjust) on key events",
      "Switch app campaign optimization goal: Conversions → Value",
      "Set min ROAS bid floor + monitor 7d learning phase",
      "Scale budget by 20-30% per week once exiting learning"
    ],
    "priority": "Critical",
    "adoption_pct": 0,
    "stage": "Pitched",
    "expected_lift": "+15-20% ROAS uplift (app)",
    "references": [
      "Meta App Advertising Playbook 2025",
      "Meta Value Optimization Benchmarks"
    ],
    "tags": "",
    "hidden_by_default": false
  },
  {
    "rank": 6,
    "solution": "Adopt related media suggestions",
    "what_it_solves": "Surface high-affinity variants to keep refresh cadence up.",
    "activate_it": [
      "Adopt related media suggestions"
    ],
    "priority": "High",
    "adoption_pct": 0,
    "stage": "Pitched",
    "expected_lift": "",
    "references": [],
    "tags": "",
    "hidden_by_default": false
  },
  {
    "rank": 7,
    "solution": "Connect external analytics to Meta",
    "what_it_solves": "Closes the loop between Meta delivery and your BI.",
    "activate_it": [
      "Connect your Google analytics tooling to Meta"
    ],
    "priority": "High",
    "adoption_pct": 0,
    "stage": "Pitched",
    "expected_lift": "Full-funnel attribution visibility",
    "references": [],
    "tags": "",
    "hidden_by_default": false
  },
  {
    "rank": 8,
    "solution": "Increase creative diversification",
    "what_it_solves": "#1 lever for BLS lift and learning-phase exit. Concentrated spend caps performance.",
    "activate_it": [
      "Audit current creative split — flag if 1 creative >40% spend",
      "Brief 3-5 distinct creative concepts per ad set (variant ≠ minor edit)",
      "Mix formats: video + static + carousel within same ad set",
      "Use Advantage+ Creative to auto-generate format variants",
      "Refresh cadence: ≥1 new concept per 2 weeks per ad set"
    ],
    "priority": "High",
    "adoption_pct": 12,
    "stage": "Actioned",
    "expected_lift": "+13% lower CPA",
    "references": [
      "Meta Creative Insights 2025",
      "Meta Creative Diversification Benchmarks"
    ],
    "tags": "",
    "hidden_by_default": false
  },
  {
    "rank": 9,
    "solution": "Advantage+ campaign budget",
    "what_it_solves": "Budget consolidation. Exits learning phase faster.",
    "activate_it": [
      "Add Advantage+ campaign budget"
    ],
    "priority": "High",
    "adoption_pct": 48,
    "stage": "Pitched",
    "expected_lift": "+12% lower CPA",
    "references": [
      "Meta Advantage+ Campaign Budget Benchmarks 2025"
    ],
    "tags": "",
    "hidden_by_default": false
  },
  {
    "rank": 10,
    "solution": "Adopt Threads Feed placement",
    "what_it_solves": "Net-new inventory. Early-mover advantage on rising surface.",
    "activate_it": [
      "Adopt Threads Feed placement"
    ],
    "priority": "Medium",
    "adoption_pct": 0,
    "stage": "Actioned",
    "expected_lift": "+10% incremental reach",
    "references": [],
    "tags": "",
    "hidden_by_default": false
  },
  {
    "rank": 11,
    "solution": "Advantage+ placements",
    "what_it_solves": "ML-optimized delivery across surfaces. Beats manual placement selection.",
    "activate_it": [
      "Advantage+  placements"
    ],
    "priority": "Medium",
    "adoption_pct": 0,
    "stage": "Pitched",
    "expected_lift": "+6% lower CPA",
    "references": [
      "Meta Advantage+ Benchmarks 2025"
    ],
    "tags": "",
    "hidden_by_default": false
  },
  {
    "rank": 12,
    "solution": "Adopt flexible media",
    "what_it_solves": "Lets system mix-and-match assets for best per-placement combo.",
    "activate_it": [
      "Enable flexible media"
    ],
    "priority": "Medium",
    "adoption_pct": 0,
    "stage": "Pitched",
    "expected_lift": "+5% CPA improvement",
    "references": [],
    "tags": "",
    "hidden_by_default": false
  },
  {
    "rank": 13,
    "solution": "Optimize your Pixel with High Intent Events",
    "what_it_solves": "",
    "activate_it": [
      "Optimize your Pixel by adding purchase events"
    ],
    "priority": "Medium",
    "adoption_pct": 0,
    "stage": "Pitched",
    "expected_lift": "",
    "references": [],
    "tags": "",
    "hidden_by_default": false
  },
  {
    "rank": 14,
    "solution": "Adopt goal-based bidding",
    "what_it_solves": "Aligns delivery to business KPI vs proxy metric.",
    "activate_it": [
      "Goal-based bidding"
    ],
    "priority": "Medium",
    "adoption_pct": 0,
    "stage": "Pitched",
    "expected_lift": "+5% lower CPA",
    "references": [],
    "tags": "",
    "hidden_by_default": false
  },
  {
    "rank": 15,
    "solution": "Adopt 'website and app' conversion location",
    "what_it_solves": "Captures cross-surface conversions otherwise lost.",
    "activate_it": [
      "Create website and app ads"
    ],
    "priority": "Medium",
    "adoption_pct": 0,
    "stage": "Pitched",
    "expected_lift": "+15-20% conversion volume uplift",
    "references": [],
    "tags": "",
    "hidden_by_default": false
  },
  {
    "rank": 16,
    "solution": "Opt into Reels (9:16 with audio)",
    "what_it_solves": "3.2× more effective for brand impressions. Core of Reels-first strategy.",
    "activate_it": [
      "Selecting Reels placements",
      "Add Music",
      "Build Reels ads assets",
      "GenAI Video Expansion for FB Reels",
      "Enable video expansion via video touch-ups"
    ],
    "priority": "Medium",
    "adoption_pct": 2,
    "stage": "Actioned",
    "expected_lift": "3.2× more effective for brand impressions",
    "references": [
      "Meta Reels Performance Report 2025"
    ],
    "tags": "",
    "hidden_by_default": true
  },
  {
    "rank": 17,
    "solution": "Gen AI Creative: Adopt text generation",
    "what_it_solves": "",
    "activate_it": [
      "Gen AI Creative: Adopt text generation"
    ],
    "priority": "Medium",
    "adoption_pct": 3,
    "stage": "Actioned",
    "expected_lift": "",
    "references": [],
    "tags": "",
    "hidden_by_default": true
  },
  {
    "rank": 18,
    "solution": "Improve CAPI event match quality",
    "what_it_solves": "Restores attribution signal lost to ATT/cookie loss.",
    "activate_it": [
      "Improve Conversions API Event Match Quality"
    ],
    "priority": "Medium",
    "adoption_pct": 4,
    "stage": "Actioned",
    "expected_lift": "+5% lower CPA + 1pt EMQ uplift",
    "references": [
      "Meta CAPI Performance Benchmarks"
    ],
    "tags": "",
    "hidden_by_default": true
  },
  {
    "rank": 19,
    "solution": "Add animation to image ads",
    "what_it_solves": "Higher CTR + completion vs static. Low-effort production lift.",
    "activate_it": [
      "Add animation to your image ads"
    ],
    "priority": "Medium",
    "adoption_pct": 12,
    "stage": "Partially adopted",
    "expected_lift": "+8% CTR lift",
    "references": [],
    "tags": "",
    "hidden_by_default": true
  },
  {
    "rank": 20,
    "solution": "Optimize account structure",
    "what_it_solves": "Same logic, account-wide. Compounding gains.",
    "activate_it": [
      "Simplify or consolidate ad sets"
    ],
    "priority": "Medium",
    "adoption_pct": 65,
    "stage": "Partially adopted",
    "expected_lift": "+5% lower CPA",
    "references": [],
    "tags": "",
    "hidden_by_default": true
  }
]
