[
  {
    "stream_name": "App Promotion test — validate Highest Volume bidding before scaling",
    "subtitle_why": "Validate bidding hypothesis before committing full Q2 budget",
    "subtitle_how": "Test backlog queued for Q2, nothing live yet",
    "theme": "App Performance",
    "status": "Open",
    "meta_owner": "Julian",
    "client_owner": "Josselyn",
    "sort_order": 1
  },
  {
    "stream_name": "Click-Based Audience Exclusion — remove existing users from targeting",
    "subtitle_why": "Improve net new reach efficiency, reduce wasted spend",
    "subtitle_how": "Awaiting ad account ID list from MWM",
    "theme": "App Performance",
    "status": "Open",
    "meta_owner": "Julian",
    "client_owner": "Josselyn",
    "sort_order": 2
  },
  {
    "stream_name": "Predicted Lifetime Value (pLTV) — blended optimization rollout",
    "subtitle_why": "Unlock Value Optimization targeting high-LTV users",
    "subtitle_how": "Blended scoring model shared with Meta, scope undefined",
    "theme": "App Performance",
    "status": "Open",
    "meta_owner": "Julian + Horia",
    "client_owner": "Josselyn",
    "sort_order": 3
  },
  {
    "stream_name": "Advantage+ App Campaign — Highest Volume bid consolidation test",
    "subtitle_why": "Scale winning creatives with controlled budget across accounts",
    "subtitle_how": "Beta queue confirmed, weekly rollout in progress",
    "theme": "App Performance",
    "status": "In Progress",
    "meta_owner": "Julian",
    "client_owner": "Josselyn",
    "sort_order": 4,
    "link_url": "https://docs.google.com/spreadsheets/d/1jq5CbXugwqKo3PmcjfA2CfIE-u_iP0BGnKM6lnOOL8s/edit?gid=109251479#gid=109251479"
  },
  {
    "stream_name": "Audience Explorer Boosting (AEB) — de-boost killing delivery",
    "subtitle_why": "Restore delivery quality and advertiser confidence",
    "subtitle_how": "Awaiting MWM diagnostic input on affected campaigns",
    "theme": "App Performance",
    "status": "Blocked",
    "meta_owner": "Julian",
    "client_owner": "Josselyn",
    "sort_order": 5
  },
  {
    "stream_name": "Collaborative Ads for App (CASC) — full-funnel pilot",
    "subtitle_why": "Test full-funnel efficiency bridging brand and performance",
    "subtitle_how": "Deck shared to Josselyn, awaiting feedback",
    "theme": "App Performance",
    "status": "Open",
    "meta_owner": "Julian",
    "client_owner": "Josselyn",
    "sort_order": 6,
    "link_url": "https://docs.google.com/presentation/d/1XaBolEQMuB7Ogmjld5_9UB_Byes2Fo9U5uMyoZZlY4I/edit?slide=id.g3a57a2b2a18_0_0#slide=id.g3a57a2b2a18_0_0",
    "deadline": "2026-05-13"
  },
  {
    "stream_name": "Marketing API migration — Advantage+ / AAC breaking changes",
    "subtitle_why": "Protect Q2 revenue continuity from API deprecations",
    "subtitle_how": "API audit not started yet",
    "theme": "Measurement & Signals",
    "status": "Open",
    "meta_owner": "Julian",
    "client_owner": "Josselyn + Ismail",
    "sort_order": 7
  },
  {
    "stream_name": "App Re-engagement pilot — reactivate lapsed users",
    "subtitle_why": "Capture incremental revenue from existing user base",
    "subtitle_how": "No re-engagement layer active today",
    "theme": "Measurement & Signals",
    "status": "Open",
    "meta_owner": "Julian",
    "client_owner": "Josselyn",
    "sort_order": 8
  },
  {
    "stream_name": "Web-to-App signal pipeline — rebuild after Apr 21 break",
    "subtitle_why": "Restore Web-to-App campaign performance",
    "subtitle_how": "Source corrected Apr 21, monitoring new baseline",
    "theme": "Measurement & Signals",
    "status": "Blocked",
    "meta_owner": "Julian",
    "client_owner": "Josselyn",
    "sort_order": 9,
    "tags": "WAITING:Josselyn"
  },
  {
    "stream_name": "Web-to-App anomaly — Color Pop + SwipeWipe signal contamination",
    "subtitle_why": "Ensure clean optimization signal on priority apps",
    "subtitle_how": "Technical Support Center investigation in flight",
    "theme": "Measurement & Signals",
    "status": "Blocked",
    "meta_owner": "Julian + TSC",
    "client_owner": "Ismail",
    "sort_order": 10,
    "tags": "WAITING:Josselyn (14d overdue)"
  },
  {
    "stream_name": "Creative tracking gap — Sincerely Off My Chest app (CAPI dedup)",
    "subtitle_why": "Validate animated creative performance measurement",
    "subtitle_how": "Awaiting MWM technical investigation",
    "theme": "Measurement & Signals",
    "status": "Blocked",
    "meta_owner": "Julian",
    "client_owner": "Josselyn",
    "sort_order": 11
  },
  {
    "stream_name": "Conversions API (CAPI) signal quality — hashed parameters missing",
    "subtitle_why": "Lift attribution accuracy and delivery quality",
    "subtitle_how": "Awaiting MWM decision on signal collection expansion",
    "theme": "Measurement & Signals",
    "status": "Blocked",
    "meta_owner": "Julian",
    "client_owner": "Josselyn",
    "sort_order": 12
  },
  {
    "stream_name": "Static-to-Animated creative migration Q2",
    "subtitle_why": "Capture performance lift from animated ad formats",
    "subtitle_how": "Top performing static creatives not yet identified",
    "theme": "Creative & Formats",
    "status": "Open",
    "meta_owner": "Julian",
    "client_owner": "Josselyn",
    "sort_order": 13
  },
  {
    "stream_name": "Threads placement activation — reach younger audiences",
    "subtitle_why": "Expand reach in Gen Z demographics via new placement",
    "subtitle_how": "Placement unchecked on many live campaigns",
    "theme": "Creative & Formats",
    "status": "Open",
    "meta_owner": "Julian",
    "client_owner": "Josselyn",
    "sort_order": 14,
    "link_url": "https://docs.google.com/presentation/d/1XaBolEQMuB7Ogmjld5_9UB_Byes2Fo9U5uMyoZZlY4I/edit?slide=id.g34fcf147ce7_0_0#slide=id.g34fcf147ce7_0_0"
  },
  {
    "stream_name": "Partnership Ads expansion — scale proven ROAS win to more apps",
    "subtitle_why": "SwipeWipe pilot delivered 13% ROAS vs 6% BAU, replicate across portfolio",
    "subtitle_how": "Pilot results validated, expansion planning",
    "theme": "Creative & Formats",
    "status": "In Progress",
    "meta_owner": "Julian",
    "client_owner": "Josselyn",
    "sort_order": 15,
    "link_url": "https://docs.google.com/presentation/d/1XaBolEQMuB7Ogmjld5_9UB_Byes2Fo9U5uMyoZZlY4I/edit?slide=id.g359053d8fb6_1_31#slide=id.g359053d8fb6_1_31"
  },
  {
    "stream_name": "Custom Label Audiences beta — audience-level bid optimization",
    "subtitle_why": "Enable granular bid adjustments per audience segment",
    "subtitle_how": "Beta access available via Value Rules path",
    "theme": "AI / Innovation",
    "status": "Open",
    "meta_owner": "Julian",
    "client_owner": "Josselyn",
    "sort_order": 16
  },
  {
    "stream_name": "AI Connectors — connect MWM AI platform to Meta Ads data",
    "subtitle_why": "Enable AI-powered ad optimization using Meta data feeds",
    "subtitle_how": "Connectors launched Apr 30, awaiting client feedback",
    "theme": "AI / Innovation",
    "status": "In Progress",
    "meta_owner": "Julian",
    "client_owner": "Josselyn + Benjamin",
    "sort_order": 17
  },
  {
    "stream_name": "Business AI — expand access to large advertiser accounts",
    "subtitle_why": "Unlock account-level AI insights at MWM scale",
    "subtitle_how": "Currently SMB-only allowlist, large advertisers excluded",
    "theme": "AI / Innovation",
    "status": "Blocked",
    "meta_owner": "Julian",
    "client_owner": "Josselyn",
    "sort_order": 18
  },
  {
    "stream_name": "Picnic onboarding — Meta UA strategy post-acquisition",
    "subtitle_why": "Stand up dedicated Picnic workstream within MWM",
    "subtitle_how": "Scope session not yet scheduled",
    "theme": "Strategic Account",
    "status": "Open",
    "meta_owner": "Julian + Rafael",
    "client_owner": "Josselyn + Charles",
    "sort_order": 19
  },
  {
    "stream_name": "MWM onsite + exec lunch",
    "subtitle_why": "Reset strategic alignment with leadership",
    "subtitle_how": "Completed",
    "theme": "Strategic Account",
    "status": "Done",
    "meta_owner": "Julian + Rafael + Gilles",
    "client_owner": "Josselyn + Charles + Benjamin",
    "sort_order": 20,
    "pinned": true,
    "deadline": "TODAY"
  },
  {
    "stream_name": "Monthly cadence with Benjamin (VP Growth)",
    "subtitle_why": "Formalize strategic rhythm with VP Growth",
    "subtitle_how": "Completed",
    "theme": "Strategic Account",
    "status": "Done",
    "meta_owner": "Julian",
    "client_owner": "Benjamin",
    "sort_order": 21,
    "pinned": true,
    "deadline": "TODAY"
  },
  {
    "stream_name": "Picnic hand-over — transfer from Rebecca Schatz (UK team)",
    "subtitle_why": "Complete account seat transfer post-acquisition",
    "subtitle_how": "Operational hand-off in progress",
    "theme": "Strategic Account",
    "status": "In Progress",
    "meta_owner": "Julian + Rafael",
    "client_owner": "Charles",
    "sort_order": 22
  },
  {
    "stream_name": "Brand Lift / Conversion Lift Study — first scalable branding test",
    "subtitle_why": "Convince VP Growth (Benjamin) on branding investment value",
    "subtitle_how": "Pre-condition for formalizing monthly cadence",
    "theme": "Measurement & Signals",
    "status": "Open",
    "meta_owner": "Julian",
    "client_owner": "Benjamin",
    "sort_order": 23,
    "deadline": "2026-05-13"
  },
  {
    "stream_name": "Value Rules — custom audience bid adjustments implementation",
    "subtitle_why": "Q2 optimization lever across full app portfolio",
    "subtitle_how": "Scope undefined",
    "theme": "App Performance",
    "status": "Open",
    "meta_owner": "Julian",
    "client_owner": "Josselyn",
    "sort_order": 24
  },
  {
    "stream_name": "Purchase Event troubleshooting — Free Trial conversion confusion",
    "subtitle_why": "Clarify conversion event signal quality for optimization",
    "subtitle_how": "Awaiting campaign data from Josselyn",
    "theme": "Measurement & Signals",
    "status": "Blocked",
    "meta_owner": "Julian",
    "client_owner": "Josselyn",
    "sort_order": 25,
    "tags": "WAITING:Josselyn"
  },
  {
    "stream_name": "Meta-funded Partnership Ads test (MPA credits program)",
    "subtitle_why": "Use Meta-funded credits before expiration deadline",
    "subtitle_how": "0.4% Partnership Ads penetration, needs green-light",
    "theme": "Creative & Formats",
    "status": "Open",
    "meta_owner": "Julian + Rafael",
    "client_owner": "Xavier + McKenna",
    "sort_order": 26,
    "pinned": true,
    "link_url": "https://meta.highspot.com/items/68c884354e9a8abb2496b235",
    "deadline": "2026-06-30"
  },
  {
    "stream_name": "Technical betas session with Horia (BizEng)",
    "subtitle_why": "Scope AEB de-boost fix + Value Rules with engineering team",
    "subtitle_how": "Meeting not yet scheduled",
    "theme": "App Performance",
    "status": "Open",
    "meta_owner": "Julian",
    "client_owner": "Horia",
    "sort_order": 27
  },
  {
    "stream_name": "Check next Meta event in Dubai — potential MWM presence",
    "subtitle_why": "Event opportunity for client relationship",
    "subtitle_how": "From Tech Pod notes May 7",
    "theme": "App Performance",
    "status": "Open",
    "meta_owner": "Julian",
    "client_owner": "—",
    "sort_order": 28
  },
  {
    "stream_name": "Attributed Revenue discrepancy — animation-to-static Sincerely Off My Chest",
    "subtitle_why": "CRM attribution accuracy for creative format decisions",
    "subtitle_how": "Raised in Apr 29 weekly call with Josselyn",
    "theme": "Measurement & Signals",
    "status": "Open",
    "meta_owner": "Julian",
    "client_owner": "Josselyn",
    "sort_order": 29
  },
  {
    "stream_name": "Web-to-App purchases event — simplify data request to Josselyn",
    "subtitle_why": "Unblock investigation with lighter data ask",
    "subtitle_how": "Previous request too complex, reformulate",
    "theme": "Measurement & Signals",
    "status": "Open",
    "meta_owner": "Julian",
    "client_owner": "Josselyn",
    "sort_order": 30
  },
  {
    "stream_name": "Partnership Ads Automation test — automate workflow at scale",
    "subtitle_why": "Reduce manual setup time for Partnership Ads campaigns",
    "subtitle_how": "Email sent to Josselyn, status unknown",
    "theme": "Creative & Formats",
    "status": "Open",
    "meta_owner": "Julian",
    "client_owner": "Josselyn",
    "sort_order": 31
  },
  {
    "stream_name": "Creative Shop London event — review deck",
    "subtitle_why": "Creative inspiration and event preparation",
    "subtitle_how": "Deck available",
    "theme": "Creative & Formats",
    "status": "Open",
    "meta_owner": "Julian",
    "client_owner": "—",
    "sort_order": 32
  }
]